reddit_mcp/__init__.py
reddit_mcp/config.py
reddit_mcp/reddit_client.py
reddit_mcp/server.py
reddit_mcp_tool-0.2.1.dist-info/METADATA
reddit_mcp_tool-0.2.1.dist-info/WHEEL
reddit_mcp_tool-0.2.1.dist-info/entry_points.txt
reddit_mcp_tool-0.2.1.dist-info/RECORD
