Metadata-Version: 2.4
Name: reddit-mcp-tool
Version: 0.2.1
Summary: Reddit MCP server for reading and searching Reddit content
Author-email: GeLi2001 <geli2001@berkeley.edu>
License: MIT
Keywords: api,mcp,model-context-protocol,reddit,search
Classifier: Development Status :: 4 - Beta
Classifier: Intended Audience :: Developers
Classifier: License :: OSI Approved :: MIT License
Classifier: Programming Language :: Python :: 3
Classifier: Programming Language :: Python :: 3.10
Classifier: Programming Language :: Python :: 3.11
Classifier: Programming Language :: Python :: 3.12
Classifier: Topic :: Internet :: WWW/HTTP :: Dynamic Content
Classifier: Topic :: Software Development :: Libraries :: Python Modules
Requires-Python: >=3.10
Requires-Dist: asyncpraw>=7.7.1
Requires-Dist: fastmcp>=0.4.0
Requires-Dist: praw>=7.7.1
Requires-Dist: python-dotenv>=1.0.0
Provides-Extra: dev
Requires-Dist: black>=23.0.0; extra == 'dev'
Requires-Dist: pytest>=7.0.0; extra == 'dev'
Requires-Dist: ruff>=0.1.0; extra == 'dev'
